tai/__init__.py
tai/cli.py
tai/config.py
terminal_ai_assistant-4.0.0.dist-info/METADATA
terminal_ai_assistant-4.0.0.dist-info/WHEEL
terminal_ai_assistant-4.0.0.dist-info/entry_points.txt
terminal_ai_assistant-4.0.0.dist-info/top_level.txt
terminal_ai_assistant-4.0.0.dist-info/RECORD
