Metadata-Version: 2.4
Name: terminal-ai-assistant
Version: 4.0.0
Summary: tAI, a terminal AI assistant
Author: Bjarne Oeverli
Author-email: bjarneocodes@gmail.com
Requires-Dist: anthropic
Requires-Dist: google-generativeai
Requires-Dist: groq
Requires-Dist: inquirer
Requires-Dist: openai
Requires-Dist: rich
Dynamic: author
Dynamic: author-email
Dynamic: description
Dynamic: description-content-type
Dynamic: requires-dist
Dynamic: summary
